webview_proc/.gitignore
webview_proc/__init__.py
webview_proc/_version.py
webview_proc/webview_proc.py
webview_proc-0.1.0rc7.dist-info/METADATA
webview_proc-0.1.0rc7.dist-info/WHEEL
webview_proc-0.1.0rc7.dist-info/licenses/LICENSE
webview_proc-0.1.0rc7.dist-info/RECORD
