Metadata-Version: 2.4
Name: webview-proc
Version: 0.1.0rc7
Summary: A Python package for running pywebview windows in a separate thread, providing a synchronous API for stable and isolated webview management.
Project-URL: Homepage, https://github.com/10x-concepts/webview-proc
Project-URL: Repository, https://github.com/10x-concepts/webview-proc
Project-URL: Issues, https://github.com/10x-concepts/webview-proc/issues
Project-URL: Documentation, https://github.com/10x-concepts/webview-proc#readme
Author-email: Ilya Pevzner <iap@10xconcepts.com>
License: MIT License
License-File: LICENSE
Keywords: api,gui,pywebview,subprocess,synchronous
Classifier: Development Status :: 3 - Alpha
Classifier: Intended Audience :: Developers
Classifier: License :: OSI Approved :: MIT License
Classifier: Operating System :: OS Independent
Classifier: Programming Language :: Python :: 3
Classifier: Programming Language :: Python :: 3.9
Classifier: Programming Language :: Python :: 3.10
Classifier: Programming Language :: Python :: 3.11
Classifier: Programming Language :: Python :: 3.12
Classifier: Programming Language :: Python :: 3.13
Classifier: Programming Language :: Python :: 3.14
Classifier: Topic :: Software Development :: Libraries :: Python Modules
Classifier: Topic :: Software Development :: User Interfaces
Requires-Python: >=3.9
Requires-Dist: pywebview>=6.0
Provides-Extra: dev
Requires-Dist: pytest-cov>=6.0; extra == 'dev'
Requires-Dist: pytest>=7.0; extra == 'dev'
Requires-Dist: ruff>=0.14; extra == 'dev'
Requires-Dist: uv>=0.9; extra == 'dev'
